ArtSnake/__init__.py
ArtSnake/adaptive_watermark_creation.py
ArtSnake/detect_watermark.py
ArtSnake/insert_watermark.py
ArtSnake/measure_diff.py
ArtSnake/poison_image.py
ArtSnake/remove_watermarks.py
ArtSnake-0.3.0.dist-info/METADATA
ArtSnake-0.3.0.dist-info/WHEEL
ArtSnake-0.3.0.dist-info/top_level.txt
ArtSnake-0.3.0.dist-info/RECORD
