Metadata-Version: 2.1
Name: ArtSnake
Version: 0.3.0
Summary: A brief description of your library
Home-page: https://github.com/MekhyW/ArtSnake
Author: Andre Melo, Felipe Catapano and Rafael Katri
Author-email: your@email.com
License: MIT
Requires-Dist: numpy
Requires-Dist: opencv-python
Requires-Dist: Pillow
Requires-Dist: torch
Requires-Dist: torchvision
Requires-Dist: timm
Requires-Dist: setuptools
